README.md
setup.cfg
setup.py
campaign_planning_tool/__init__.py
campaign_planning_tool/_campaign_planning_tool.py
campaign_planning_tool/_export.py
campaign_planning_tool/_generate_layers.py
campaign_planning_tool/_plot.py
campaign_planning_tool/_points_optimization.py
campaign_planning_tool/_trajectory_optimization.py
campaign_planning_tool.egg-info/PKG-INFO
campaign_planning_tool.egg-info/SOURCES.txt
campaign_planning_tool.egg-info/dependency_links.txt
campaign_planning_tool.egg-info/not-zip-safe
campaign_planning_tool.egg-info/requires.txt
campaign_planning_tool.egg-info/top_level.txt