Metadata-Version: 2.1
Name: campaign-planning-tool
Version: 0.1.3
Summary: Python library for scanning lidar campaign planning
Home-page: https://github.com/niva83/campaign-planning-tool
Author: Nikola Vasiljevic
Author-email: niva@dtu.dk
License: UNKNOWN
Platform: UNKNOWN
Classifier: Development Status :: 4 - Beta
Classifier: Intended Audience :: Developers
Classifier: Topic :: Software Development :: Build Tools
Classifier: License :: OSI Approved :: BSD License
Classifier: Programming Language :: Python :: 3.7
Requires-Python: >=3.7
